oc_logging/Logging.py
oc_logging/__init__.py
oc_logging/setup.py
oc_logging/wrapper.py
oc_logging/test/__init__.py
oc_logging/test/test.py
oc_logging-1.1.7.dist-info/licenses/LICENSE
oc_logging-1.1.7.dist-info/METADATA
oc_logging-1.1.7.dist-info/WHEEL
oc_logging-1.1.7.dist-info/top_level.txt
oc_logging-1.1.7.dist-info/RECORD
