Metadata-Version: 2.4
Name: oc-logging
Version: 1.1.7
Summary: Custom Development python API logging libraries
License: Apache2.0
Requires-Python: >=3.6
License-File: LICENSE
Requires-Dist: requests
Requires-Dist: packaging
Requires-Dist: structlog
Dynamic: description
Dynamic: description-content-type
Dynamic: license
Dynamic: license-file
Dynamic: requires-dist
Dynamic: requires-python
Dynamic: summary
